{"cameraMode":{"drawMode":0,"name":"Shaded","section":"Shading Mode"},"sceneLighting":true,"audioPlay":false,"sceneViewState":{"m_AlwaysRefresh":false,"showFog":true,"showSkybox":true,"showFlares":true,"showImageEffects":true,"showParticleSystems":true,"showVisualEffectGraphs":true,"m_FxEnabled":true},"in2DMode":false,"pivot":{"x":233.4293212890625,"y":350.98223876953127,"z":169.28720092773438},"rotation":{"x":0.3687010109424591,"y":-0.5474308729171753,"z":0.29150956869125368,"w":0.6923962831497192},"size":4.217790603637695,"orthographic":false}